muirmap/__init__.py
muirmap/_modidx.py
muirmap/biophysical.py
muirmap/core.py
muirmap/experiments.py
muirmap/raster.py
muirmap/visualization.py
muirmap/demo/__init__.py
muirmap/demo/execute_invest/__init__.py
muirmap/demo/execute_invest/execute_invest_carbon.py
muirmap/demo/execute_invest/execute_invest_ndr.py
muirmap/demo/execute_invest/execute_invest_sdr.py
muirmap/demo/execute_invest/execute_invest_seasonal_water_yield.py
muirmap/demo/execute_invest/with_logging.py
muirmap-0.0.1.dist-info/licenses/LICENSE
muirmap-0.0.1.dist-info/METADATA
muirmap-0.0.1.dist-info/WHEEL
muirmap-0.0.1.dist-info/entry_points.txt
muirmap-0.0.1.dist-info/top_level.txt
muirmap-0.0.1.dist-info/RECORD
